Metadata-Version: 1.0
Name: xontrib-schedule
Version: 0.0.1
Summary: Xonsh Task Scheduling
Home-page: https://github.com/astronouth7303/xontrib-schedule
Author: Jamie Bliss
Author-email: astronouth7303@gmail.com
License: MIT
Platform: any
